__init__.py
wandr.py
data/__init__.py
WANDR-0.5.0.dist-info/LICENSE
WANDR-0.5.0.dist-info/METADATA
WANDR-0.5.0.dist-info/WHEEL
WANDR-0.5.0.dist-info/top_level.txt
WANDR-0.5.0.dist-info/RECORD
